masterpy/__init__.py
masterpy/util.py
masterpy/models/GeosseModel.py
masterpy/models/SirModel.py
masterpy/models/TODO.md
masterpy/models/__init__.py
masterpy/models/classe_model.py
masterpy/models/cont_trait_model.py
masterpy/models/model.py
masterpy-0.0.1.dist-info/METADATA
masterpy-0.0.1.dist-info/WHEEL
masterpy-0.0.1.dist-info/licenses/LICENSE
masterpy-0.0.1.dist-info/RECORD
